Workbook
Name Slicer_Seller_s_Name: #N/A
Name Slicer_Product: #N/A

Sheet SellersNew
A1: Seller's Name | B1: Region | C1: Product | D1: Sales
A2: Home Depo | B2: Central | C2: Pencil | D2: 3330
A3: Costco | B3: Central | C3: Eraser | D3: 6688
A4: BestBuy | B4: Central | C4: Notebook | D4: 6450
A5: Walmart | B5: East | C5: Book | D5: 3036
A6: Staples | B6: South | C6: Shopner | D6: 3744
A7: Amazon | B7: South | C7: Bag | D7: 7656
A8: FlipCart | B8: South | C8: Pen | D8: 2925
A9: Home Depo | B9: South | C9: Pencil | D9: 4810
A10: Costco | B10: South | C10: Pen | D10: 6688
A11: Home Depo | B11: South | C11: Pencil | D11: 3870
A12: Costco | B12: West | C12: Eraser | D12: 4290
A13: BestBuy | B13: South | C13: Notebook | D13: 4224
... A30: Costco | B30: South | C30: Pencil | D30: 3404

Sheet PivotTable
A3: Region | B3: Sum of Sales
A4: Central | B4: 0.25105448 | C4: =B4 -> 0.25105448 | D4: =1-C4 -> 0.74894552 | E4: 1
A5: East | B5: 0.15836718 | C5: =B5 -> 0.15836718 | D5: =1-C5 -> 0.84163282 | E5: 1
A6: South | B6: 0.48424152 | C6: =B6 -> 0.48424152 | D6: =1-C6 -> 0.51575848 | E6: 1
A7: West | B7: 0.10633682 | C7: =B7 -> 0.10633682 | D7: =1-C7 -> 0.89366318 | E7: 1
A8: Grand Total | B8: 1

Sheet Sell_Data
A1: Order Date | B1: Full Name | C1: Region | D1: Product | E1: Quantity | F1: Price | G1: Amount
A2: 13/01/2021 | B2: Robert Patel | C2: Central | D2: Pencil | E2: 74 | F2: 45 | G2: 3330
A3: 14/01/2022 | B3: Cameron Lo | C3: Central | D3: Eraser | E3: 76 | F3: 88 | G3: 6688
A4: 14/02/2027 | B4: Harper Castillo | C4: Central | D4: Notebook | E4: 86 | F4: 75 | G4: 6450
A5: 14/05/2025 | B5: Harper Dominguez | C5: East | D5: Book | E5: 66 | F5: 46 | G5: 3036
A6: 14/08/2019 | B6: Ezra Vu | C6: South | D6: Shopner | E6: 48 | F6: 78 | G6: 3744
A7: 14/12/2023 | B7: Jade Hu | C7: South | D7: Bag | E7: 87 | F7: 88 | G7: 7656
A8: 15/01/2018 | B8: Miles Chang | C8: South | D8: Pen | E8: 65 | F8: 45 | G8: 2925
A9: 15/03/2020 | B9: Gianna Holmes | C9: South | D9: Pencil | E9: 74 | F9: 65 | G9: 4810
A10: 15/07/2024 | B10: Jameson Thomas | C10: South | D10: Pen | E10: 76 | F10: 88 | G10: 6688
A11: 15/07/2026 | B11: Jameson Pena | C11: South | D11: Pencil | E11: 86 | F11: 45 | G11: 3870
A12: 15/11/2022 | B12: Bella Wu | C12: West | D12: Eraser | E12: 66 | F12: 65 | G12: 4290
A13: 16/07/2023 | B13: Jose Wong | C13: South | D13: Notebook | E13: 48 | F13: 88 | G13: 4224
... A86: 10/09/2024 | B86: Xavier Patel | C86: South | D86: Pen | E86: 74 | F86: 75 | G86: 5550
A87: 45638 | B87: Robert Soto | C87: West | D87: Pencil | E87: 76 | F87: 46 | G87: 3496
A88: 05/10/2025 | B88: Nevaeh Jiang | C88: South | D88: Eraser | E88: 86 | F88: 45 | G88: 3870
A89: 06/04/2025 | B89: Chloe Reyes | C89: West | D89: Notebook | E89: 66 | F89: 65 | G89: 4290
A90: 08/01/2025 | B90: Lucy Edwards | C90: West | D90: Book | E90: 48 | F90: 88 | G90: 4224
A91: 09/07/2025 | B91: Luna Edwards | C91: West | D91: Shopner | E91: 87 | F91: 75 | G91: 6525
A92: 02/03/2026 | B92: Stella Daniels | C92: West | D92: Bag | E92: 65 | F92: 46 | G92: 2990
A93: 04/06/2026 | B93: Ayla Ma | C93: West | D93: Pen | E93: 74 | F93: 78 | G93: 5772
A94: 07/01/2026 | B94: Matthew Avila | C94: Central | D94: Pencil | E94: 76 | F94: 45 | G94: 3420
A95: 07/09/2026 | B95: Gianna Lim | C95: South | D95: Pen | E95: 86 | F95: 65 | G95: 5590
A96: 46307 | B96: Joseph Tan | C96: South | D96: Pencil | E96: 66 | F96: 88 | G96: 5808
A97: 11/04/2026 | B97: Connor Lai | C97: South | D97: Eraser | E97: 48 | F97: 75 | G97: 3600
A98: 06/01/2027 | B98: Ava Owens | C98: East | D98: Notebook | E98: 87 | F98: 46 | G98: 4002
A99: 09/04/2027 | B99: Dylan Aguilar | C99: East | D99: Book | E99: 65 | F99: 78 | G99: 5070

Sheet Sellers Data
A1: Order Date | B1: Seller's Name | C1: Region | D1: Product | E1: Quantity | F1: Price | G1: Amount
A2: 13/01/2021 | B2: Home Depo | C2: Central | D2: Pencil | E2: 74 | F2: 45 | G2: 3330
A3: 14/01/2022 | B3: Costco | C3: Central | D3: Eraser | E3: 76 | F3: 88 | G3: 6688
A4: 14/02/2027 | B4: BestBuy | C4: Central | D4: Notebook | E4: 86 | F4: 75 | G4: 6450
A5: 14/05/2025 | B5: Walmart | C5: East | D5: Book | E5: 66 | F5: 46 | G5: 3036
A6: 14/08/2019 | B6: Staples | C6: South | D6: Shopner | E6: 48 | F6: 78 | G6: 3744
A7: 14/12/2023 | B7: Amazon | C7: South | D7: Bag | E7: 87 | F7: 88 | G7: 7656
A8: 15/01/2018 | B8: FlipCart | C8: South | D8: Pen | E8: 65 | F8: 45 | G8: 2925
A9: 15/03/2020 | B9: Home Depo | C9: South | D9: Pencil | E9: 74 | F9: 65 | G9: 4810
A10: 15/07/2024 | B10: Costco | C10: South | D10: Pen | E10: 76 | F10: 88 | G10: 6688
A11: 15/07/2026 | B11: Home Depo | C11: South | D11: Pencil | E11: 86 | F11: 45 | G11: 3870
A12: 15/11/2022 | B12: Costco | C12: West | D12: Eraser | E12: 66 | F12: 65 | G12: 4290
A13: 16/07/2023 | B13: BestBuy | C13: South | D13: Notebook | E13: 48 | F13: 88 | G13: 4224
... A30: 21/02/2024 | B30: Costco | C30: South | D30: Pencil | E30: 74 | F30: 46 | G30: 3404

Sheet Sheet1
A1: Employee Data Sheet
A4: Employee ID | B4: Full Name | C4: Job Title | D4: Department | E4: Business Unit | F4: Gender | G4: Ethnicity | H4: Age | I4: Hire Date | J4: Annual Salary And Bonus
A5: E02002 | B5: Kai Le | C5: Controls Engineer | D5: Engineering | E5: Manufacturing | F5: Male | G5: Asian | H5: 47 | I5: 46088 | J5: 40499
A6: E02012 | B6: Jameson Pena | C6: Systems Analyst | D6: IT | E6: Manufacturing | F6: Male | G6: Latino | H6: 49 | I6: 44962 | J6: 45703
A7: E02003 | B7: Robert Patel | C7: Analyst | D7: Sales | E7: Corporate | F7: Male | G7: Asian | H7: 58 | I7: 45327 | J7: 54811
A8: E02019 | B8: Ivy Chau | C8: Analyst | D8: Sales | E8: Specialty Products | F8: Female | G8: Asian | H8: 61 | I8: 45693 | J8: 64208
A9: E02017 | B9: Luna Lu | C9: IT Systems Architect | D9: IT | E9: Corporate | F9: Female | G9: Asian | H9: 62 | I9: 46058 | J9: 66227
A10: E02007 | B10: Ezra Vu | C10: Network Administrator | D10: IT | E10: Manufacturing | F10: Male | G10: Asian | H10: 62 | I10: 46423 | J10: 69674
A11: E02009 | B11: Miles Chang | C11: Analyst II | D11: Finance | E11: Corporate | F11: Male | G11: Asian | H11: 62 | I11: 46788 | J11: 70000
A12: E02019 | B12: Bella Wu | C12: Director | D12: IT | E12: Corporate | F12: Female | G12: Asian | H12: 67 | I12: 46096 | J12: 70000
A13: E02013 | B13: Bella Wu | C13: Sr. Analyst | D13: Finance | E13: Specialty Products | F13: Female | G13: Asian | H13: 63 | I13: 47154 | J13: 83323
A14: E02023 | B14: Lillian Lewis | C14: Technical Architect | D14: IT | E14: Research & Development | F14: Female | G14: Black | H14: 43 | I14: 47519 | J14: 83576
A15: E02004 | B15: Cameron Lo | C15: Network Administrator | D15: IT | E15: Research & Development | F15: Male | G15: Asian | H15: 34 | I15: 47884 | J15: 89744
A16: E02008 | B16: Jade Hu | C16: Sr. Analyst | D16: Accounting | E16: Specialty Products | F16: Female | G16: Asian | H16: 58 | I16: 48249 | J16: 92368
A17: E02020 | B17: Jordan Kumar | C17: Service Desk Analyst | D17: IT | E17: Specialty Products | F17: Male | G17: Asian | H17: 29 | I17: 37906 | J17: 95729
... A27: E02018 | B27: Bella Tran | C27: Vice President | D27: Engineering | E27: Specialty Products | F27: Female | G27: Asian | H27: 45 | I27: 41559 | J27: 254486

Sheet Sheet13
A1: Full Name | B1: Sales | C1: Target | D1: Commission
A2: Kai Lei | B2: 2500 | C2: 3000 | D2: =B2*2% -> 50
A3: Robert Pat | B3: 3000 | C3: 5000 | D3: =B3*2% -> 60
A4: Cameron | B4: 3500 | C4: 4000 | D4: =B4*2% -> 70
A5: Harper Cas | B5: 4500 | C5: 6000 | D5: =B5*2% -> 90
A6: HarperDo | B6: 2500 | C6: 4000 | D6: =B6*2% -> 50
A7: Ezra Vu | B7: 3100 | C7: 4000 | D7: =B7*2% -> 62
A8: Jade Hu | B8: 3300 | C8: 4500 | D8: =B8*2% -> 66
A9: Miles Char | B9: 2500 | C9: 3000 | D9: =B9*2% -> 50
A10: Gianna Ho | B10: 3000 | C10: 3500 | D10: =B10*2% -> 60
A11: Jameson T | B11: 4000 | C11: 5000 | D11: =B11*2% -> 80
A12: Jameson P | B12: 4500 | C12: 5000 | D12: =B12*2% -> 90
A13: Bella Wu | B13: 5000 | C13: 7000 | D13: =B13*2% -> 100
... A27: Charles Sir | B27: 3000 | C27: 4500 | D27: =B27*2% -> 60

Sheet School-Result
A1: School Result
A3: Name | B3: Father's Name | C3: English | D3: Sanskrit | E3: Hindi | F3: Math | G3: Science | H3: Gujarati
A4: Ramesh | B4: Mr.Mohan | C4: 35 | D4: 45 | E4: 65 | F4: 77 | G4: 95 | H4: 77
A5: Manish | B5: Mr.Sohan | C5: 55 | D5: 65 | E5: 74 | F5: 80 | G5: 85 | H5: 79
A6: Pratik | B6: Mr.Shah | C6: 67 | D6: 88 | E6: 76 | F6: 79 | G6: 99 | H6: 89
A7: Chetan | B7: Mr.Rohit | C7: 64 | D7: 75 | E7: 86 | F7: 75 | G7: 90 | H7: 85
A8: Ketan | B8: Mr.Mohit | C8: 78 | D8: 46 | E8: 66 | F8: 90 | G8: 77 | H8: 69
A9: Shiva | B9: Mr.Patel | C9: 88 | D9: 78 | E9: 48 | F9: 95 | G9: 89 | H9: 88
A10: Jaydev | B10: Mr.Roy | C10: 56 | D10: 88 | E10: 87 | F10: 98 | G10: 56 | H10: 54

Sheet Sheet11
A1: Name | B1: English | C1: Sanskrit | D1: Hindi | E1: Math | F1: Science | G1: Gujarati
A2: Ramesh | B2: 35 | C2: 45 | D2: 65 | E2: 77 | F2: 95 | G2: 77
A3: Manish | B3: 55 | C3: 65 | D3: 74 | E3: 80 | F3: 85 | G3: 79
A4: Pratik | B4: 67 | C4: 88 | D4: 76 | E4: 79 | F4: 99 | G4: 89
A5: Chetan | B5: 64 | C5: 75 | D5: 86 | E5: 75 | F5: 90 | G5: 85
A6: Ketan | B6: 78 | C6: 46 | D6: 66 | E6: 90 | F6: 77 | G6: 69
A7: Shiva | B7: 88 | C7: 78 | D7: 48 | E7: 95 | F7: 89 | G7: 88
A8: Jaydev | B8: 56 | C8: 88 | D8: 87 | E8: 98 | F8: 56 | G8: 54

Sheet Sheet4
A1: Name | B1: Mobile Number | C1: Product | D1: Rate | E1: Quantity | F1: Amount
A2: Ramesh | B2: 1234567890 | C2: Pen | D2: 45 | E2: 65 | F2: =D2*E2 -> 2925
A3: Manish | C3: Pencil | D3: 65 | E3: 74 | F3: =D3*E3 -> 4810
A4: Pratik | C4: Eraser | D4: 88 | E4: 76 | F4: =D4*E4 -> 6688
A5: Chetan | C5: Notebook | D5: 75 | E5: 86 | F5: =D5*E5 -> 6450
A6: Ketan | C6: Book | D6: 46 | E6: 66 | F6: =D6*E6 -> 3036
A7: Shiva | C7: Shopner | D7: 78 | E7: 48 | F7: =D7*E7 -> 3744
A8: Jaydev | C8: Bag | D8: 88 | E8: 87 | F8: =D8*E8 -> 7656

Sheet Employee
A1: Employee | B1: Full Name | C1: Sales | D1: Target | E1: Commission
A2: E02002 | B2: Kai Lei | C2: 2500 | D2: 3000 | E2: =C2*2% -> 50
A3: E02003 | B3: Robert Pat | C3: 3000 | D3: 5000 | E3: =C3*2% -> 60
A4: E02004 | B4: Cameron | C4: 3500 | D4: 4000 | E4: =C4*2% -> 70
A5: E02005 | B5: Harper Cas | C5: 4500 | D5: 6000 | E5: =C5*2% -> 90
A6: E02006 | B6: HarperDo | C6: 2500 | D6: 4000 | E6: =C6*2% -> 50
A7: E02007 | B7: Ezra Vu | C7: 3100 | D7: 4000 | E7: =C7*2% -> 62
A8: E02008 | B8: Jade Hu | C8: 3300 | D8: 4500 | E8: =C8*2% -> 66
A9: E02009 | B9: Miles Char | C9: 2500 | D9: 3000 | E9: =C9*2% -> 50
A10: E02010 | B10: Gianna Ho | C10: 3000 | D10: 3500 | E10: =C10*2% -> 60
A11: E02011 | B11: Jameson T | C11: 4000 | D11: 5000 | E11: =C11*2% -> 80
A12: E02012 | B12: Jameson P | C12: 4500 | D12: 5000 | E12: =C12*2% -> 90
A13: E02013 | B13: Bella Wu | C13: 5000 | D13: 7000 | E13: =C13*2% -> 100
... A26: E02025 | B26: Parker Lai | C26: 2700 | D26: 4500 | E26: =C26*2% -> 54

Sheet Shakra-Practice-Test-1
A1: Employee ID | B1: Department | C1: Sales 2022 | D1: Sales 2023 | E1: Sales Target 2023
A2: 101 | B2: Marketing | C2: 20000 | D2: 20000 | E2: 21000 | G2: Question - 1
A3: 102 | B3: Sales | C3: 15000 | D3: 18000 | E3: 17000 | G3: What was the sales target of employee ID '111' in 2023? Use two different Formulas. | M3: =MATCH(A12,A1:A16,0) -> 12
A4: 103 | B4: HR | C4: 12000 | D4: 11000 | E4: 12500 | G4: Answer - 1 | H4: =VLOOKUP(A12,A1:E16,5,0) -> 23500 | J4: Answer - 2 | L4: =_xlfn.XLOOKUP(A12,A1:A16,E1:E16,0) -> 23500 | N4: =INDEX(E1:E16,MATCH(A12,A1:A16,0)) -> 23500
A5: 104 | B5: IT | C5: 18000 | D5: 19000 | E5: 18500
A6: 105 | B6: Marketing | C6: 16000 | D6: 16200 | E6: 16500 | G6: Question - 2
A7: 106 | B7: Sales | C7: 22000 | D7: 21000 | E7: 22500 | G7: Extract the first two letters from any department name in the dataset.
A8: 107 | B8: IT | C8: 21000 | D8: 21500 | E8: 21200 | G8: Answer | H8: =LEFT(B2,4) -> Mark | I8: =LEFT(B14,2) -> Sa
A9: 108 | B9: HR | C9: 17000 | D9: 18000 | E9: 17500 | H9: =RIGHT(B2,3) -> ing | I9: =RIGHT(B11,3) -> les
A10: 109 | B10: Marketing | C10: 21000 | D10: 23000 | E10: 22000 | G10: Question - 3
A11: 110 | B11: Sales | C11: 19000 | D11: 19000 | E11: 20000 | G11: Determine the sales target for the employee who achieved the highest sales in 2023.
A12: 111 | B12: IT | C12: 23000 | D12: 24000 | E12: 23500 | G12: Answer | H12: =_xlfn.XLOOKUP(MAX(D2:D16),D2:D16,E2:E16,0) -> 26000
A13: 112 | B13: Marketing | C13: 18000 | D13: 17500 | E13: 19000 | H13: =INDEX(E1:E16,MATCH(MAX(D1:D16),D1:D16,0)) -> 26000
A14: 113 | B14: Sales | C14: 16500 | D14: 17500 | E14: 17200 | G14: Question - 4
A15: 114 | B15: Marketing | C15: 15800 | D15: 16800 | E15: 16000 | G15: Retrieve the total sales from 2022 for "IT" department without using direct references.
A16: 115 | B16: IT | C16: 25000 | D16: 24500 | E16: 26000 | G16: Answer | H16: =SUMIFS(C1:C16,B1:B16,"IT") -> 87000
G18: Question - 5
G19: How many employees from the IT and Marketing departments combined are there in the dataset?
G20: Answer | H20: {=SUM(COUNTIFS(B1:B16,{"IT","Marketing"}))} -> 9
G22: Question - 6
G23: Apply conditional formatting to highlight rows of all employees who exceeded their 2023 sales target.

Sheet Shakra-Practise-Test-2
A1: Zone | B1: Month | C1: City Code | D1: City | E1: Category | F1: Sales | G1: Sales Units | H1: Margin | I1: LY Monthly Sales | J1: LY Monthly Sales Units | K1: LY Monthly Margin
A2: West | B2: January | C2: 548 | D2: Mumbai | E2: Winter Wear | F2: 98886 | G2: 3820 | H2: 38300 | I2: 105960 | J2: 3590 | K2: 39568
A3: West | B3: January | C3: 548 | D3: Mumbai | E3: Beach Wear | F3: 106704 | G3: 7390 | H3: 58883 | I3: 106635 | J3: 7343 | K3: 57099
A4: West | B4: January | C4: 548 | D4: Mumbai | E4: Hoodie | F4: 90853 | G4: 7854 | H4: 41528 | I4: 82859 | J4: 7505 | K4: 39255
A5: West | B5: January | C5: 548 | D5: Mumbai | E5: Tees | F5: 172932 | G5: 19681 | H5: 44840 | I5: 204580 | J5: 21439 | K5: 43161
A6: West | B6: January | C6: 548 | D6: Mumbai | E6: Jeans | F6: 128875 | G6: 10402 | H6: 43788 | I6: 120982 | J6: 11637 | K6: 48466
A7: East | B7: January | C7: 578 | D7: Kolkata | E7: Winter Wear | F7: 158067 | G7: 5398 | H7: 55941 | I7: 203272 | J7: 7470 | K7: 62022
A8: East | B8: January | C8: 578 | D8: Kolkata | E8: Beach Wear | F8: 150608 | G8: 9536 | H8: 83194 | I8: 140719 | J8: 10161 | K8: 78722
A9: East | B9: January | C9: 578 | D9: Kolkata | E9: Hoodie | F9: 109605 | G9: 9328 | H9: 52498 | I9: 117689 | J9: 9396 | K9: 56309
A10: East | B10: January | C10: 578 | D10: Kolkata | E10: Tees | F10: 200031 | G10: 18254 | H10: 60268 | I10: 273262 | J10: 30363 | K10: 51993
A11: East | B11: January | C11: 578 | D11: Kolkata | E11: Jeans | F11: 159164 | G11: 12046 | H11: 57471 | I11: 152046 | J11: 14631 | K11: 43129
A12: South | B12: January | C12: 659 | D12: Chennai | E12: Winter Wear | F12: 77544 | G12: 3548 | H12: 34076 | I12: 120827 | J12: 2963 | K12: 46341
A13: South | B13: January | C13: 659 | D13: Chennai | E13: Beach Wear | F13: 125966 | G13: 6530 | H13: 54881 | I13: 101682 | J13: 7487 | K13: 53061
... A126: North | B126: May | C126: 737 | D126: Delhi | E126: Jeans | F126: 97020 | G126: 10079 | H126: 35455 | I126: 131575 | J126: 9384 | K126: 42858

Sheet Equality Class
A1: Factory | B1: Job Role | C1: Equality Score | D1: Equality class
A2: Daikibo Factory Meiyo | B2: C-Level | C2: -25 | D2: =IF(ABS(C2)<=10,"Fair",IF(ABS(C2)<=20,"Unfair","Highly Discriminative")) -> Highly Discriminative
A3: Daikibo Factory Meiyo | B3: VP | C3: -26 | D3: =IF(ABS(C3)<=10,"Fair",IF(ABS(C3)<=20,"Unfair","Highly Discriminative")) -> Highly Discriminative
A4: Daikibo Factory Meiyo | B4: Director | C4: -19 | D4: =IF(ABS(C4)<=10,"Fair",IF(ABS(C4)<=20,"Unfair","Highly Discriminative")) -> Unfair
A5: Daikibo Factory Meiyo | B5: Sr. Manager | C5: -15 | D5: =IF(ABS(C5)<=10,"Fair",IF(ABS(C5)<=20,"Unfair","Highly Discriminative")) -> Unfair
A6: Daikibo Factory Meiyo | B6: Manager | C6: -14 | D6: =IF(ABS(C6)<=10,"Fair",IF(ABS(C6)<=20,"Unfair","Highly Discriminative")) -> Unfair
A7: Daikibo Factory Meiyo | B7: Jr. Manager | C7: -20 | D7: =IF(ABS(C7)<=10,"Fair",IF(ABS(C7)<=20,"Unfair","Highly Discriminative")) -> Unfair
A8: Daikibo Factory Meiyo | B8: Sr. Engineer | C8: -5 | D8: =IF(ABS(C8)<=10,"Fair",IF(ABS(C8)<=20,"Unfair","Highly Discriminative")) -> Fair
A9: Daikibo Factory Meiyo | B9: Engineer | C9: -8 | D9: =IF(ABS(C9)<=10,"Fair",IF(ABS(C9)<=20,"Unfair","Highly Discriminative")) -> Fair
A10: Daikibo Factory Meiyo | B10: Jr. Engineer | C10: 3 | D10: =IF(ABS(C10)<=10,"Fair",IF(ABS(C10)<=20,"Unfair","Highly Discriminative")) -> Fair
A11: Daikibo Factory Meiyo | B11: Operational Support | C11: -22 | D11: =IF(ABS(C11)<=10,"Fair",IF(ABS(C11)<=20,"Unfair","Highly Discriminative")) -> Highly Discriminative
A12: Daikibo Factory Meiyo | B12: Machine Operator | C12: -7 | D12: =IF(ABS(C12)<=10,"Fair",IF(ABS(C12)<=20,"Unfair","Highly Discriminative")) -> Fair
A13: Daikibo Factory Seiko | B13: VP | C13: -19 | D13: =IF(ABS(C13)<=10,"Fair",IF(ABS(C13)<=20,"Unfair","Highly Discriminative")) -> Unfair
... A38: Daikibo Shenzhen | B38: Machine Operator | C38: -7 | D38: =IF(ABS(C38)<=10,"Fair",IF(ABS(C38)<=20,"Unfair","Highly Discriminative")) -> Fair

Sheet Task-2
I4: Add a best suitable chart for Sales, LY Sales & Margin Rate (only one chart)
B5: Month | C5: Sales | D5: LY Sales | E5: Margin | F5: Margin Rate
B6: January
B7: February
B8: March
B9: April
B10: May
B12: Hint: Margin rate=(Margin/Sales)*100

Sheet Task-3
A2: Add a pivot table for for each Zone/City, include sales,margin,margin rate, add slicer for Month, sort by sales

Sheet Task-1
B3: Q1. Calculate Total Sales & Total Sales Units
B5: Total Sales
B6: Total Sales Unit
B9: Q2. Fill in below tables with Sales
B11: City Name | C11: City Code | D11: Jan | E11: Feb | F11: Mar
B12: Kolkata
B13: Mumbai
B14: Delhi
B17: Q3
B18: Can you filter your data only for West region where Sales Unit is greater than 7000
B20: Zone | C20: Month | D20: City Code | E20: City | F20: Category | G20: Sales | H20: Sales Units | I20: Margin | J20: LY Weekly Sales | K20: LY Weekly Sales Units | L20: LY Weekly Margin

Sheet Task-4
M2: Product Table | Q2: Order Table
B3: Student Name | C3: Subject | D3: Marks | X3: How many records would results in each of the following conditions?
B4: Alex | C4: English | D4: 70 | M4: Product Id | N4: Product Name | Q4: Order Id | R4: Product Id | S4: Qty | X4: Table 1 | Z4: Table 2
B5: Alex | C5: Math | D5: 68 | M5: 1 | N5: Munch | Q5: 101 | R5: 1 | S5: 100 | X5: Num | Z5: Num
B6: Alex | C6: Geography | D6: 32 | M6: 2 | N6: Bournville | Q6: 102 | R6: 3 | S6: 30 | X6: 1 | Z6: 1
B7: Bob | C7: English | D7: 91 | M7: 3 | N7: Kitkat | Q7: 103 | R7: 1 | S7: 40 | X7: 0 | Z7: 0
B8: Bob | C8: Math | D8: 43 | M8: 4 | N8: Dairy Milk | X8: 1 | Z8: 2
B9: Bob | C9: Geography | D9: 24 | Z9: 1
B10: Charlie | C10: English | D10: 56
B11: Charlie | C11: Math | D11: 55
B12: Charlie | C12: Geography | D12: 79
X13: Left Join
B14: Q: Find out student name who secures highest marks for each subject using SQL query | M14: Q: Find products that were never purchased by any customers using SQL Query | X14: Right Join
X15: Inner Join

Sheet Vlookup
A1: Employee | B1: Full Name | C1: Sales | D1: Target | E1: Commission | G1: Employee | H1: Sales
A2: E02013 | B2: {=VLOOKUP(A2,Employee!A1:E26,{2,3,4,5},0)} -> Bella Wu | C2: 5000 | D2: 7000 | E2: 100 | G2: E02015 | H2: =INDEX(Employee!$A$1:$E$26,MATCH(Vlookup!$G$2,Employee!$A:$A,0),MATCH(Vlookup!H1,Employee!$A$1:$E$1,0)) -> 3000
B4: {=_xlfn.XLOOKUP($A$2,Employee!$A$1:$A$26,Employee!B1:E26)} -> Bella Wu | C4: 5000 | D4: 7000 | E4: 100
B6: =VLOOKUP($A$2,Employee!$A$1:$E$26,COLUMNS(Employee!$A$1:B1),0) -> Bella Wu | C6: =VLOOKUP($A$2,Employee!$A$1:$E$26,COLUMNS(Employee!$A$1:C1),0) -> 5000 | D6: =VLOOKUP($A$2,Employee!$A$1:$E$26,COLUMNS(Employee!$A$1:D1),0) -> 7000 | E6: =VLOOKUP($A$2,Employee!$A$1:$E$26,COLUMNS(Employee!$A$1:E1),0) -> 100
B9: {=_xlfn.XLOOKUP($A$2,Employee!$A$1:$A$26,Employee!B1:$E$26)} -> Bella Wu | C9: 5000 | D9: 7000 | E9: 100
B11: =MATCH(B1,A1:E1,0) -> 2
B12: {=_xlfn.XLOOKUP(A2,Employee!A1:A26,Employee!B1:E26,"Value not Found")} -> Bella Wu | C12: 5000 | D12: 7000 | E12: 100
B14: =INDEX(Employee!$A$1:$E$26,MATCH(Vlookup!$A$2,Employee!$A$1:$A$26,0),MATCH(Vlookup!B1,Employee!$A$1:$E$1,0)) -> Bella Wu | C14: =INDEX(Employee!$A$1:$E$26,MATCH(Vlookup!$A$2,Employee!$A$1:$A$26,0),MATCH(Vlookup!C1,Employee!$A$1:$E$1,0)) -> 5000 | D14: =INDEX(Employee!$A$1:$E$26,MATCH(Vlookup!$A$2,Employee!$A$1:$A$26,0),MATCH(Vlookup!D1,Employee!$A$1:$E$1,0)) -> 7000 | E14: =INDEX(Employee!$A$1:$E$26,MATCH(Vlookup!$A$2,Employee!$A$1:$A$26,0),MATCH(Vlookup!E1,Employee!$A$1:$E$1,0)) -> 100
